LICENSE.txt
MANIFEST.in
README.rst
pyproject.toml
setup.cfg
setup.py
SALTISE_user_feedback.egg-info/PKG-INFO
SALTISE_user_feedback.egg-info/SOURCES.txt
SALTISE_user_feedback.egg-info/dependency_links.txt
SALTISE_user_feedback.egg-info/requires.txt
SALTISE_user_feedback.egg-info/top_level.txt
user_feedback/__init__.py
user_feedback/admin.py
user_feedback/apps.py
user_feedback/models.py
user_feedback/serializers.py
user_feedback/urls.py
user_feedback/views.py
user_feedback/migrations/0001_initial.py
user_feedback/migrations/0002_auto_20200912_2239.py
user_feedback/migrations/0003_feedback_archived.py
user_feedback/migrations/0004_auto_20210424_2234.py
user_feedback/migrations/__init__.py
user_feedback/static/user_feedback/css/styles.min.css
user_feedback/static/user_feedback/js/app.min.js